{
  "events": [
    {
      "title": "QTSoc Career Panel",
      "date": "Dec 13th ",
      "duration": " ",
      "link": "https://docs.google.com/forms/d/e/1FAIpQLSd6zSvFZtMIXm4Q-MlV8ya5znX6JPXlSh9DvyR1yXfFQPGO0A/viewform?usp=sf_link",
      "duration_unit": " ",
      "content": "A chance to ask questions and interact with people working in the quantum industry and completing quantum related PhDs. These people were in the same shoes as most of you until very recently, so join us in hearing their journey into quantum."
    },
    {
      "title": "QTSoc Quantum Talk Vol. 1",
      "date": "Mar 21st 24'",
      "duration": "18:00-19:00",
      "link": "https://forms.office.com/e/RXKX35zWiH",
      "duration_unit": " ",
      "content": "Quantum computing holds the key to unlocking groundbreaking solutions for sustainability challenges. By leveraging the unparalleled processing power of quantum computers, we can optimize renewable energy distribution, enhance climate modeling accuracy, and revolutionize material science for better environmental stewardship. This transformative technology offers a promising pathway to achieving a more sustainable and resilient future for our planet."
    }
  ]
}
